pyfootball.py
pyfootball_storagehandler.py
py_football.egg-info/PKG-INFO
py_football.egg-info/SOURCES.txt
py_football.egg-info/dependency_links.txt
py_football.egg-info/entry_points.txt
py_football.egg-info/requires.txt
py_football.egg-info/top_level.txt
py_football-1.0.4.dist-info/METADATA
py_football-1.0.4.dist-info/WHEEL
py_football-1.0.4.dist-info/entry_points.txt
py_football-1.0.4.dist-info/top_level.txt
py_football-1.0.4.dist-info/RECORD
