Metadata-Version: 2.1
Name: py-football
Version: 1.0.4
Summary: Easy to install and simple way to access all Roanuz Football APIs. Its a library for showing Live Football Score, Football Schedule and Statistics
Home-page: https://github.com/roanuz/py-football
Author: Roanuz Softwares Private Ltd
Author-email: contact@roanuz.com
License: UNKNOWN
Platform: UNKNOWN
Requires-Dist: requests (>=2.19.1)
